README
setup.py
txXBee/__init__.py
txXBee/protocol.py
txXBee.egg-info/PKG-INFO
txXBee.egg-info/SOURCES.txt
txXBee.egg-info/dependency_links.txt
txXBee.egg-info/requires.txt
txXBee.egg-info/top_level.txt