Metadata-Version: 1.0
Name: txXBee
Version: 0.0.4
Summary: XBee Protocol for Twisted
Home-page: http://github.com/trunet/txxbee
Author: Wagner Sartori Junior
Author-email: wsartori@gmail.com
License: COPYING
Platform: UNKNOWN
Classifier: Framework :: Twisted
Classifier: Intended Audience :: Developers
Classifier: License :: OSI Approved :: GNU General Public License (GPL)
Classifier: Programming Language :: Python
Classifier: Topic :: Communications
Classifier: Topic :: Software Development :: Libraries :: Python Modules
Classifier: Topic :: Utilities
